lando_messaging/__init__.py
lando_messaging/clients.py
lando_messaging/messaging.py
lando_messaging/workqueue.py
lando_messaging-2.1.0.dist-info/LICENSE
lando_messaging-2.1.0.dist-info/METADATA
lando_messaging-2.1.0.dist-info/WHEEL
lando_messaging-2.1.0.dist-info/top_level.txt
lando_messaging-2.1.0.dist-info/RECORD
