Metadata-Version: 2.1
Name: lando-messaging
Version: 2.1.0
Summary: Lando workflow messaging component
Home-page: https://github.com/Duke-GCB/lando-messaging
Author: John Bradley
Author-email: john.bradley@duke.edu
License: MIT
Platform: UNKNOWN
Requires-Dist: pika (==1.1.0)
